{
  "items": [
    {
      "title": "Live Chat Application",
      "description": "Chat live with your friends.",
      "link": "https://github.com/huseyinbattal/Live-Chat-App-with-Node.js",
      "category": "Node.js"
    },
    {
      "title": "Movie Application API",
      "description": "Save your movies to database",
      "link": "https://github.com/huseyinbattal/Nodejs-Movie-Api",
      "category": "Node.js"
    },
    {
      "title": "Tic-Tac-Toe Game",
      "description": "Enjoy the game.",
      "link": "https://github.com/huseyinbattal/React-Tic-Tac-Toe-Game",
      "category": "React.js"
    },
    {
      "title": "Movie Application",
      "description": "Add, modify and delete movies.",
      "link": "https://github.com/huseyinbattal/Movie-App-with-React-Redux",
      "category": "React-Redux"
    },
    {
      "title": "To Do List",
      "description": "Keeping track of our daily tasks.",
      "link": "https://github.com/huseyinbattal/todo-list",
      "category": "React.js"
    },
    {
      "title": "Clock Application",
      "description": "See the time of your current location digitally.",
      "link": "https://github.com/huseyinbattal/Clock-with-React.js",
      "category": "React.js"
    },
    {
      "title": "Phone Book Application",
      "description": "Add your contacts to the phone book.",
      "link": "https://github.com/huseyinbattal/Phone-Book-with-React.js",
      "category": "React.js"
    },
    {
      "title": "Library API",
      "description": "Add new books to your library.",
      "link": "https://github.com/huseyinbattal/Library-Api-with-PostgreSQL-Express-",
      "category": "Node.js-PostgreSQL"
    },
    {
      "title": "GitHub Profile",
      "description": "Visit My Profile ",
      "link": "https://github.com/huseyinbattal",
      "category": "profil"
    }
    
  ]
}
